scidra/module_utils/__init__.py
scidra/module_utils/base_module.py
scidra/module_utils/models.py
scidra/module_utils/utils.py
scidra_module_utils-0.2.1.dist-info/METADATA
scidra_module_utils-0.2.1.dist-info/WHEEL
scidra_module_utils-0.2.1.dist-info/top_level.txt
scidra_module_utils-0.2.1.dist-info/RECORD
